Metadata-Version: 2.1
Name: nextdataAI
Version: 0.0.16
Home-page: https://github.com/nextdataAI/aif
Author: Paul Magos & Stefano Zanoni
Author-email: chuckpaul98@icloud.com, s.zanoni@studenti.unipi.it
Classifier: Programming Language :: Python :: 3
Classifier: Operating System :: OS Independent
Requires-Python: >=3.9
Requires-Dist: wandb
Requires-Dist: numpy
Requires-Dist: matplotlib
Requires-Dist: scipy
Requires-Dist: gym
Requires-Dist: minihack
Requires-Dist: nle
Requires-Dist: keras
Requires-Dist: tensorflow
Requires-Dist: torch
Requires-Dist: Pillow
Requires-Dist: imageio
Requires-Dist: pandas
